selenium_astride/__init__.py
selenium_astride-0.3.1.dist-info/DESCRIPTION.rst
selenium_astride-0.3.1.dist-info/METADATA
selenium_astride-0.3.1.dist-info/RECORD
selenium_astride-0.3.1.dist-info/WHEEL
selenium_astride-0.3.1.dist-info/metadata.json
selenium_astride-0.3.1.dist-info/top_level.txt
