Metadata-Version: 2.0
Name: selenium-astride
Version: 0.3.1
Summary: Framework to use Selenium loud and clear, astride. Use it with Django, Flask or your favourite web framework.
Home-page: https://github.com/reclamador/python_selenium_astride
Author: Juan Madurga
Author-email: jlmadurga@gmail.com
License: MIT license
Keywords: selenium_astride
Platform: UNKNOWN
Classifier: Development Status :: 2 - Pre-Alpha
Classifier: Intended Audience :: Developers
Classifier: License :: OSI Approved :: MIT License
Classifier: Natural Language :: English
Classifier: Programming Language :: Python :: 2
Classifier: Programming Language :: Python :: 2.7
Requires-Dist: selenium (==3.8.0)
